objgraph.py
objgraph-3.6.1.dist-info/LICENSE
objgraph-3.6.1.dist-info/METADATA
objgraph-3.6.1.dist-info/WHEEL
objgraph-3.6.1.dist-info/top_level.txt
objgraph-3.6.1.dist-info/zip-safe
objgraph-3.6.1.dist-info/RECORD
