Metadata-Version: 2.1
Name: objgraph
Version: 3.6.1
Summary: Draws Python object reference graphs with graphviz
Home-page: https://mg.pov.lt/objgraph/
Author: Marius Gedminas
Author-email: marius@gedmin.as
License: MIT
Project-URL: Source, https://github.com/mgedmin/objgraph
Keywords: object graph visualization graphviz garbage collection
Classifier: Intended Audience :: Developers
Classifier: License :: OSI Approved :: MIT License
Classifier: Operating System :: OS Independent
Classifier: Programming Language :: Python
Classifier: Programming Language :: Python :: 3.7
Classifier: Programming Language :: Python :: 3.8
Classifier: Programming Language :: Python :: 3.9
Classifier: Programming Language :: Python :: 3.10
Classifier: Programming Language :: Python :: 3.11
Classifier: Programming Language :: Python :: 3.12
Requires-Python: >=3.7
Provides-Extra: ipython
Provides-Extra: test
License-File: LICENSE
